[{"ID":249474587530625034,"XP":1500115650,"Rep":0,"Money":0,"GCooldown":1544728761,"LevelNumber":5477},{"ID":261418273009041408,"XP":6350,"Rep":1,"Money":0,"GCooldown":1544729628,"LevelNumber":11},{"ID":120877775245541378,"XP":0,"Rep":0,"Money":0,"GCooldown":0,"LevelNumber":0},{"ID":452062765973110784,"XP":1000,"Rep":1,"Money":0,"GCooldown":0,"LevelNumber":4},{"ID":507970352501227523,"XP":0,"Rep":0,"Money":0,"GCooldown":0,"LevelNumber":0},{"ID":233989576346042370,"XP":100,"Rep":0,"Money":0,"GCooldown":0,"LevelNumber":1},{"ID":217562587938816000,"XP":3650,"Rep":0,"Money":0,"GCooldown":0,"LevelNumber":8},{"ID":520853975512252437,"XP":0,"Rep":0,"Money":0,"GCooldown":0,"LevelNumber":0}]